qing_framework/__init__.py
qing_framework/qing_errors.py
qing_framework/qing_worker.py
qing_framework/qingdom.py
qing_framework-0.0.1rc0.dist-info/DESCRIPTION.rst
qing_framework-0.0.1rc0.dist-info/METADATA
qing_framework-0.0.1rc0.dist-info/RECORD
qing_framework-0.0.1rc0.dist-info/WHEEL
qing_framework-0.0.1rc0.dist-info/metadata.json
qing_framework-0.0.1rc0.dist-info/top_level.txt
