Metadata-Version: 2.0
Name: qing-framework
Version: 0.0.1rc0
Summary: The qing of pipes
Home-page: http://github.com/alsayedgamal/qing-framework
Author: AlSayedGamal
Author-email: mail.gamal@gmail.com
License: MIT
Platform: UNKNOWN
